graphs_tradke/__init__.py
graphs_tradke/heapq.py
graphs_tradke/sp.py
graphs_tradke-0.0.2.dist-info/METADATA
graphs_tradke-0.0.2.dist-info/WHEEL
graphs_tradke-0.0.2.dist-info/RECORD
