Metadata-Version: 2.3
Name: graphs_tradke
Version: 0.0.2
Summary: Package to utilize Dijkstras Shortest Path
Project-URL: Homepage, https://github.com/pypa/sampleproject
Project-URL: Bug Tracker, https://github.com/pypa/sampleproject/issues
Author-email: Tyler Radke <tylerrradke@gmail.com>
Classifier: License :: OSI Approved :: MIT License
Classifier: Operating System :: OS Independent
Classifier: Programming Language :: Python :: 3
Requires-Python: >=3.7
